freepaths/__main__.py
freepaths/animation.py
freepaths/config.py
freepaths/data.py
freepaths/default_config.py
freepaths/electron.py
freepaths/flight.py
freepaths/interface_smmm.py
freepaths/main_mfp_sampling.py
freepaths/main_tracing.py
freepaths/maps.py
freepaths/materials.py
freepaths/move.py
freepaths/output_info.py
freepaths/output_plots.py
freepaths/output_structure.py
freepaths/particle.py
freepaths/particle_types.py
freepaths/phonon.py
freepaths/post_computations.py
freepaths/progress.py
freepaths/run_particle.py
freepaths/scatterers.py
freepaths/scattering.py
freepaths/scattering_interfaces.py
freepaths/scattering_primitives.py
freepaths/scattering_semicircle.py
freepaths/scattering_types.py
freepaths/sources.py
freepaths-2.2.dist-info/METADATA
freepaths-2.2.dist-info/WHEEL
freepaths-2.2.dist-info/entry_points.txt
freepaths-2.2.dist-info/top_level.txt
freepaths-2.2.dist-info/RECORD
